{"type": "Feature", "id": 12522558, "geometry": {"type": "Point", "coordinates": [-55.092201, -34.862202]}, "properties": {"woe:id": 12522558, "woe:parent_id": 26794423, "woe:name": "Capitan Corbeta C A Curbelo Airport", "woe:placetype": 14, "woe:placetype_name": "Airport", "woe:lang": "ENG", "iso:country": "UY", "meta:provider": ["geoplanet:7.3.1", "geoplanet:7.3.2", "geoplanet:7.4.0", "geoplanet:7.4.1", "geoplanet:7.5.1", "geoplanet:7.5.2", "geoplanet:7.6.0", "geoplanet:7.8.1", "geoplanet:7.9.0", "geoplanet:7.10.0", "geoplanet:8.0.0", "woeplanet:8.0.0"], "meta:indexed": "2020-08-20T20:26:15.615467", "meta:updated": "2020-10-14T11:46:15.847792", "woe:hierarchy": {"continent": 24865673, "country": 23424979, "town": 0, "planet": 1, "county": 0, "suburb": 0, "state": 2347648, "region": 0, "localadmin": 0}, "woe:timezone_id": 28350777, "woe:hash": "6cbcdme0fwt8", "woe:centroid": [-55.092201, -34.862202], "geom:latitude": -34.862202, "geom:longitude": -55.092201, "geom:hash": "6cbcdme0fwt8", "woe:latitude": -34.862202, "geom:centroid": [-55.092201, -34.862202], "woe:longitude": -55.092201, "woe:repo": "woeplanet-airport-uy", "geom:area": 0.0, "woe:scale": 19}}